{
    "securityType": "basic",
    "roleAttributeName": "role",
    "allowServiceSave": false,
    "basicConfiguration": {
        "securityClassName": ""
     },
    "oidcConfiguration": {
        "issuerLocationUrl": "",
        "clientId": "",
        "clientSecret": "",
        "enabled": false,
        "roleClaimPropertyName": "",
        "incomingAdminRoles": ""
    },
    "users": [{
            "userId": "admin",
            "password": "F6FDFFE48C908DEB0F4C3BD36C032E72",
            "attributes": [],
            "roles": [
                "user",
                "administrator",
                "query designer"
            ]
        }
    ],
    "roles": [
        {
            "name": "administrator",
            "description": "adminsitrator role"
        },
        {
            "name": "query designer",
            "description": "query designer role"
        }
    ]
}
